README.rst
dt_send_answers.py
setup.py
dt_send_answers.egg-info/PKG-INFO
dt_send_answers.egg-info/SOURCES.txt
dt_send_answers.egg-info/dependency_links.txt
dt_send_answers.egg-info/top_level.txt