Metadata-Version: 1.0
Name: dt-send-answers
Version: 0.1.2
Summary: Code to help Docassemble Toolkit users store answers to their interviews
Home-page: https://github.com/communitylawyer/dt_send_answers
Author: Community.lawyer, PBC
Author-email: hello@community.lawyer
License: MIT
Platform: UNKNOWN
